e4client/__init__.py
e4client-1.12.data/scripts/e4client
e4client-1.12.dist-info/DESCRIPTION.rst
e4client-1.12.dist-info/METADATA
e4client-1.12.dist-info/RECORD
e4client-1.12.dist-info/WHEEL
e4client-1.12.dist-info/metadata.json
e4client-1.12.dist-info/top_level.txt
