Metadata-Version: 2.0
Name: e4client
Version: 1.12
Summary: Client to download information of the E4 Connect platform.
Home-page: UNKNOWN
Author: khvilaboa
Author-email: UNKNOWN
License: UNKNOWN
Platform: UNKNOWN
Requires-Dist: requests
